logship/__init__.py
logship/const.py
logship/emitter.py
logship/handlers.py
py_logging_logship-0.1.47.dist-info/LICENSE
py_logging_logship-0.1.47.dist-info/METADATA
py_logging_logship-0.1.47.dist-info/WHEEL
py_logging_logship-0.1.47.dist-info/top_level.txt
py_logging_logship-0.1.47.dist-info/RECORD
