Metadata-Version: 2.1
Name: py-logging-logship
Version: 0.1.47
Summary: Python logship logging handler.
Home-page: https://github.com/logship/py-logging-logship
Author: Andrey Maslov
Author-email: info@logship.io
License: MIT
Platform: UNKNOWN
Classifier: Development Status :: 4 - Beta
Classifier: Intended Audience :: Developers
Classifier: License :: OSI Approved :: MIT License
Classifier: Operating System :: OS Independent
Classifier: Programming Language :: Python :: 3
Classifier: Topic :: Software Development :: Libraries :: Python Modules
Classifier: Topic :: System :: Logging
Classifier: Topic :: Internet :: WWW/HTTP
Requires-Python: >=3.6
Requires-Dist: rfc3339
Requires-Dist: requests
Requires-Dist: unpaddedbase64
